racetrack_client/__init__.py
racetrack_client/__main__.py
racetrack_client/main.py
racetrack_client/py.typed
racetrack_client/client/__init__.py
racetrack_client/client/call.py
racetrack_client/client/deploy.py
racetrack_client/client/env.py
racetrack_client/client/logs.py
racetrack_client/client/manage.py
racetrack_client/client/move.py
racetrack_client/client/run.py
racetrack_client/client/socketio.py
racetrack_client/client_config/__init__.py
racetrack_client/client_config/alias.py
racetrack_client/client_config/auth.py
racetrack_client/client_config/client_config.py
racetrack_client/client_config/io.py
racetrack_client/client_config/remote.py
racetrack_client/client_config/update.py
racetrack_client/log/__init__.py
racetrack_client/log/context_error.py
racetrack_client/log/errors.py
racetrack_client/log/exception.py
racetrack_client/log/logs.py
racetrack_client/manifest/__init__.py
racetrack_client/manifest/load.py
racetrack_client/manifest/manifest.py
racetrack_client/manifest/merge.py
racetrack_client/manifest/schema.json
racetrack_client/manifest/validate.py
racetrack_client/plugin/__init__.py
racetrack_client/plugin/install.py
racetrack_client/plugin/plugin_manifest.py
racetrack_client/plugin/bundler/__init__.py
racetrack_client/plugin/bundler/bundle.py
racetrack_client/plugin/bundler/filename_matcher.py
racetrack_client/utils/__init__.py
racetrack_client/utils/auth.py
racetrack_client/utils/byte.py
racetrack_client/utils/config.py
racetrack_client/utils/datamodel.py
racetrack_client/utils/env.py
racetrack_client/utils/quantity.py
racetrack_client/utils/request.py
racetrack_client/utils/semver.py
racetrack_client/utils/shell.py
racetrack_client/utils/strings.py
racetrack_client/utils/table.py
racetrack_client/utils/time.py
racetrack_client/utils/url.py
racetrack_client-2.35.1.dist-info/LICENSE
racetrack_client-2.35.1.dist-info/METADATA
racetrack_client-2.35.1.dist-info/WHEEL
racetrack_client-2.35.1.dist-info/entry_points.txt
racetrack_client-2.35.1.dist-info/top_level.txt
racetrack_client-2.35.1.dist-info/RECORD
