Metadata-Version: 2.2
Name: racetrack-client
Version: 2.35.1
Summary: CLI client tool for deploying workloads to Racetrack
Home-page: https://github.com/TheRacetrack/racetrack
Author: ERST
Author-email: noreply@erst.dk
License: Apache License 2.0
Classifier: Programming Language :: Python :: 3
Classifier: Operating System :: OS Independent
Classifier: License :: OSI Approved :: Apache Software License
Classifier: Intended Audience :: Information Technology
Requires-Python: >=3.8.0
License-File: LICENSE
Requires-Dist: PyYAML>=6.0.1
Requires-Dist: pydantic>=2.0
Requires-Dist: backoff>=2.2
Requires-Dist: python-socketio[client]>=5.8
Requires-Dist: typer>=0.15.1
Requires-Dist: jsonschema>=4.17.3
Dynamic: author
Dynamic: author-email
Dynamic: classifier
Dynamic: description
Dynamic: description-content-type
Dynamic: home-page
Dynamic: license
Dynamic: requires-dist
Dynamic: requires-python
Dynamic: summary
